phenospy/__init__.py
phenospy/cli.py
phenospy/nl_fun.py
phenospy/nl_owlToMd.py
phenospy/nl_owlToMd_fun.py
phenospy/owl_make_phsOntology.py
phenospy/owl_owlready_config.py
phenospy/owl_xml2owl_fun.py
phenospy/owl_xmlToOwl.py
phenospy/phs_addXmlMeta.py
phenospy/phs_grammar.py
phenospy/phs_mainConvert.py
phenospy/phs_parser_fun.py
phenospy/phs_various_fun.py
phenospy/phs_xml.py
phenospy/phs_xmlTranslateTerms.py
phenospy/snips_fun.py
phenospy/snips_makeFromYaml.py
phenospy/snips_readFromJSON.py
phenospy/utils.py
phenospy/xml_recodeThis.py
phenospy/package-data/.DS_Store
phenospy/package-data/phenoscript.obda
phenospy/package-data/phenoscript.owl
phenospy/package-data/phenoscript.properties
phenospy/package-data/phs-config.yaml
phenospy/package-data/snippets-default.json
phenospy-0.231.dist-info/LICENSE.txt
phenospy-0.231.dist-info/METADATA
phenospy-0.231.dist-info/WHEEL
phenospy-0.231.dist-info/entry_points.txt
phenospy-0.231.dist-info/top_level.txt
phenospy-0.231.dist-info/RECORD
