Metadata-Version: 2.1
Name: phenospy
Version: 0.231
Summary: Tools for making and processing computable phenotypes
Home-page: https://github.com/sergeitarasov/PhenoScript
Author: Sergei Tarasov
Author-email: sergei.tarasov@helsinki.fi
License: MIT
Project-URL: Project Logo, https://raw.githubusercontent.com/sergeitarasov/PhenoScript/main/Phenoscript_logo.png
Classifier: Development Status :: 3 - Alpha
Classifier: License :: OSI Approved :: MIT License
Classifier: Programming Language :: Python :: 3
Classifier: Programming Language :: Python :: 3.6
Classifier: Programming Language :: Python :: 3.7
Classifier: Programming Language :: Python :: 3.8
Classifier: Programming Language :: Python :: 3.9
Classifier: Topic :: Scientific/Engineering :: Bio-Informatics
License-File: LICENSE.txt
Requires-Dist: Owlready2
Requires-Dist: PyYAML
Requires-Dist: colorama
Requires-Dist: markdown
Requires-Dist: pyparsing ==2.4.2
